jobrunner/__init__.py
jobrunner/config.py
jobrunner/create_or_update_jobs.py
jobrunner/job_executor.py
jobrunner/models.py
jobrunner/project.py
jobrunner/queries.py
jobrunner/record_stats.py
jobrunner/reusable_actions.py
jobrunner/run.py
jobrunner/service.py
jobrunner/sync.py
jobrunner/cli/__init__.py
jobrunner/cli/add_job.py
jobrunner/cli/extract_stats.py
jobrunner/cli/flags.py
jobrunner/cli/kill_job.py
jobrunner/cli/local_run.py
jobrunner/cli/prepare_for_reboot.py
jobrunner/cli/retry_job.py
jobrunner/executors/__init__.py
jobrunner/executors/local.py
jobrunner/executors/logging.py
jobrunner/lib/__init__.py
jobrunner/lib/database.py
jobrunner/lib/docker.py
jobrunner/lib/docker_stats.py
jobrunner/lib/git.py
jobrunner/lib/github_validators.py
jobrunner/lib/log_utils.py
jobrunner/lib/lru_dict.py
jobrunner/lib/path_utils.py
jobrunner/lib/string_utils.py
jobrunner/lib/subprocess_utils.py
jobrunner/lib/system_stats.py
jobrunner/lib/yaml_utils.py
opensafely_jobrunner-2.52.4.dist-info/LICENSE
opensafely_jobrunner-2.52.4.dist-info/METADATA
opensafely_jobrunner-2.52.4.dist-info/WHEEL
opensafely_jobrunner-2.52.4.dist-info/entry_points.txt
opensafely_jobrunner-2.52.4.dist-info/top_level.txt
opensafely_jobrunner-2.52.4.dist-info/RECORD
