Metadata-Version: 2.1
Name: opensafely-jobrunner
Version: 2.52.4
Home-page: https://github.com/opensafely-core/job-runner
Author: OpenSAFELY
Author-email: tech@opensafely.org
Classifier: License :: OSI Approved :: GNU General Public License v3 (GPLv3)
Requires-Python: >=3.8
License-File: LICENSE
Requires-Dist: ruamel.yaml
Requires-Dist: requests
